flask_management_blueprint/__init__.py
flask_management_blueprint/management/__init__.py
flask_management_blueprint/management/app_info.py
flask_management_blueprint/management/health_check.py
flask_management_blueprint/management/health_status.py
flask_management_blueprint/management/management_resource.py
flask_management_blueprint-0.1.0.dist-info/DESCRIPTION.rst
flask_management_blueprint-0.1.0.dist-info/METADATA
flask_management_blueprint-0.1.0.dist-info/RECORD
flask_management_blueprint-0.1.0.dist-info/WHEEL
flask_management_blueprint-0.1.0.dist-info/metadata.json
flask_management_blueprint-0.1.0.dist-info/top_level.txt
samples/__init__.py
samples/api.py
samples/run.py
tests/unit/__init__.py
tests/unit/management/__init__.py
tests/unit/management/test_app_info.py
tests/unit/management/test_health_check.py
