Metadata-Version: 2.0
Name: flask-management-blueprint
Version: 0.1.0
Summary: Flask Management Blueprint
Home-page: https://github.com/stone-payments/flask-management-blueprint
Author: UNKNOWN
Author-email: UNKNOWN
License: UNKNOWN
Platform: UNKNOWN
Requires-Dist: aiofiles
Requires-Dist: flask
Requires-Dist: websockets
